fauxcyrillic/__init__.py
fauxcyrillic/cli.py
fauxcyrillic/utils.py
fauxcyrillic-0.0.1.dist-info/LICENSE
fauxcyrillic-0.0.1.dist-info/METADATA
fauxcyrillic-0.0.1.dist-info/WHEEL
fauxcyrillic-0.0.1.dist-info/entry_points.txt
fauxcyrillic-0.0.1.dist-info/top_level.txt
fauxcyrillic-0.0.1.dist-info/RECORD
