Metadata-Version: 2.1
Name: fauxcyrillic
Version: 0.0.1
Summary: Command-line utility to convert Latin text to faux Cyrillic
Home-page: https://gitlab.com/dkreeft/fauxcyrillic
Author: Davey Kreeft
Author-email: dkreeft@xccelerated.io
License: UNKNOWN
Platform: UNKNOWN
Classifier: License :: OSI Approved :: BSD License
Classifier: Operating System :: OS Independent
Classifier: Programming Language :: Python :: 3
Requires-Python: >=3.6
Requires-Dist: Click (>=7.0.0)
Provides-Extra: build
Requires-Dist: pytest ; extra == 'build'
Requires-Dist: pytest-flake8 ; extra == 'build'
Requires-Dist: pytest-cov ; extra == 'build'
Requires-Dist: setuptools (>=38.6.0) ; extra == 'build'
Requires-Dist: twine (>=1.11.0) ; extra == 'build'
Requires-Dist: wheel (>=0.31.0) ; extra == 'build'
Provides-Extra: dev
Requires-Dist: pytest ; extra == 'dev'
Requires-Dist: pytest-flake8 ; extra == 'dev'
Requires-Dist: pytest-cov ; extra == 'dev'
